statue/__init__.py
statue/__main__.py
statue/cache.py
statue/command.py
statue/command_builder.py
statue/commands_filter.py
statue/commands_map.py
statue/commands_map_builder.py
statue/constants.py
statue/context.py
statue/context_specification.py
statue/evaluation.py
statue/exceptions.py
statue/io_util.py
statue/runner.py
statue/sources_finder.py
statue/sources_locks_repository.py
statue/verbosity.py
statue/cli/__init__.py
statue/cli/cli.py
statue/cli/cli_util.py
statue/cli/commands.py
statue/cli/common_flags.py
statue/cli/contexts.py
statue/cli/history.py
statue/cli/run.py
statue/cli/show_tree.py
statue/cli/string_util.py
statue/cli/styled_strings.py
statue/cli/templates.py
statue/cli/config/__init__.py
statue/cli/config/config_cli.py
statue/cli/config/config_commands.py
statue/cli/config/config_contexts.py
statue/cli/config/config_general.py
statue/cli/config/config_init.py
statue/cli/config/config_show.py
statue/cli/config/config_sources.py
statue/cli/config/interactive_adders/__init__.py
statue/cli/config/interactive_adders/adders_utils.py
statue/cli/config/interactive_adders/interactive_command_adder.py
statue/cli/config/interactive_adders/interactive_context_adder.py
statue/cli/config/interactive_adders/interactive_sources_adder.py
statue/config/__init__.py
statue/config/commands_repository.py
statue/config/configuration.py
statue/config/contexts_repository.py
statue/config/sources_repository.py
statue/templates/__init__.py
statue/templates/templates_provider.py
statue/templates/default_templates/__init__.py
statue/templates/default_templates/defaults.toml
statue-0.0.19.dist-info/LICENSE
statue-0.0.19.dist-info/METADATA
statue-0.0.19.dist-info/WHEEL
statue-0.0.19.dist-info/entry_points.txt
statue-0.0.19.dist-info/top_level.txt
statue-0.0.19.dist-info/RECORD
