Metadata-Version: 2.1
Name: statue
Version: 0.0.19
Summary: All your static code analysis tools, in one place
Home-page: https://github.com/saroad2/statue
Author: Sagi Shadur
Author-email: saroad2@gmail.com
Maintainer: Sagi Shadur
Maintainer-email: saroad2@gmail.com
License: Apache License
Keywords: formatting,static,code,analysis
Platform: any
Classifier: Development Status :: 3 - Alpha
Classifier: Intended Audience :: Developers
Classifier: License :: OSI Approved :: BSD License
Classifier: Operating System :: OS Independent
Classifier: Programming Language :: Python :: 3
Classifier: Programming Language :: Python :: 3.7
Classifier: Programming Language :: Python :: 3.8
Classifier: Programming Language :: Python :: 3.9
Classifier: Programming Language :: Python :: 3.10
Classifier: Programming Language :: Python :: 3 :: Only
Classifier: Topic :: Software Development :: Quality Assurance
Classifier: Topic :: Software Development :: Testing
Classifier: Topic :: Utilities
Requires-Python: >=3.7
License-File: LICENSE
Requires-Dist: tomli (>=2.0.1)
Requires-Dist: tomli-w (>=1.0.0)
Requires-Dist: click (>=8.1.3)
Requires-Dist: click-params (>=0.3.0)
Requires-Dist: tqdm (>=4.64.0)
Requires-Dist: GitPython (>=3.1.27)
Requires-Dist: types-mock (>=4.0.13)
Requires-Dist: types-toml (>=0.10.7)
Requires-Dist: types-setuptools (>=57.4.14)
Requires-Dist: importlib-resources (>=5.7.1) ; python_version < "3.9"
